{
  "VERSION": 1,
  "REVISION": 12,
  "ROW_COUNT": 36,
  "COLUMN_COUNT": 8,
  "TEXT_COUNT": 2,
  "ROW_VALIDATOR": 0,
  "COLUMN_VALIDATOR": 0,
  "HAS_ROW_NAMES": true,
  "HAS_COLUMN_NAMES": true,
  "HAS_ROW_VALIDITY": true,
  "HAS_COLUMN_VALIDITY": true,
  "HAS_UNKNOWN_BITMASK": false,
  "HAS_ROW_INDICES": true,
  "TABLE_ID": 0,
  "columnValidity": {
    "": "0",
    "name": "1",
    "hue": "0",
    "saturation": "0",
    "lightness": "0",
    "color_id": "0",
    "explanation": "1",
    "icon": "1"
  },
  "columnTypes": {
    "": -1,
    "name": 0,
    "hue": -1,
    "saturation": -1,
    "lightness": -1,
    "color_id": -1,
    "explanation": 0,
    "icon": 1
  },
  "columnTypes2": {
    "": -1,
    "name": 12,
    "hue": -1,
    "saturation": -1,
    "lightness": -1,
    "color_id": -1,
    "explanation": 12,
    "icon": 1
  },
  "COLUMN_INDICES": [
    0,
    1,
    2,
    3,
    4,
    5,
    6,
    7
  ],
  "0": {
    "": {
      "icon": 0,
      "reARMP_isValid": "0",
      "reARMP_rowIndex": 0
    }
  },
  "1": {
    "hostess_01": {
      "icon": 0,
      "reARMP_isValid": "0",
      "reARMP_rowIndex": 1
    }
  },
  "2": {
    "hostess_02": {
      "icon": 0,
      "reARMP_isValid": "0",
      "reARMP_rowIndex": 2
    }
  },
  "3": {
    "hostess_03": {
      "icon": 0,
      "reARMP_isValid": "0",
      "reARMP_rowIndex": 3
    }
  },
  "4": {
    "hostess_04": {
      "icon": 0,
      "reARMP_isValid": "0",
      "reARMP_rowIndex": 4
    }
  },
  "5": {
    "hostess_05": {
      "icon": 0,
      "reARMP_isValid": "0",
      "reARMP_rowIndex": 5
    }
  },
  "6": {
    "hostess_06": {
      "icon": 0,
      "reARMP_isValid": "0",
      "reARMP_rowIndex": 6
    }
  },
  "7": {
    "hostess_07": {
      "icon": 0,
      "reARMP_isValid": "0",
      "reARMP_rowIndex": 7
    }
  },
  "8": {
    "hostess_08": {
      "icon": 0,
      "reARMP_isValid": "0",
      "reARMP_rowIndex": 8
    }
  },
  "9": {
    "hostess_09": {
      "icon": 0,
      "reARMP_isValid": "0",
      "reARMP_rowIndex": 9
    }
  },
  "10": {
    "hostess_10": {
      "icon": 0,
      "reARMP_isValid": "0",
      "reARMP_rowIndex": 10
    }
  },
  "11": {
    "hostess_11": {
      "icon": 0,
      "reARMP_isValid": "0",
      "reARMP_rowIndex": 11
    }
  },
  "12": {
    "hostess_12": {
      "icon": 0,
      "reARMP_isValid": "0",
      "reARMP_rowIndex": 12
    }
  },
  "13": {
    "hostess_13": {
      "icon": 0,
      "reARMP_isValid": "0",
      "reARMP_rowIndex": 13
    }
  },
  "14": {
    "hostess_14": {
      "icon": 0,
      "reARMP_isValid": "0",
      "reARMP_rowIndex": 14
    }
  },
  "15": {
    "hostess_15": {
      "icon": 0,
      "reARMP_isValid": "0",
      "reARMP_rowIndex": 15
    }
  },
  "16": {
    "hostess_16": {
      "icon": 0,
      "reARMP_isValid": "0",
      "reARMP_rowIndex": 16
    }
  },
  "17": {
    "hostess_17": {
      "icon": 0,
      "reARMP_isValid": "0",
      "reARMP_rowIndex": 17
    }
  },
  "18": {
    "hostess_18": {
      "icon": 0,
      "reARMP_isValid": "0",
      "reARMP_rowIndex": 18
    }
  },
  "19": {
    "hostess_19": {
      "icon": 0,
      "reARMP_isValid": "0",
      "reARMP_rowIndex": 19
    }
  },
  "20": {
    "hostess_20": {
      "icon": 0,
      "reARMP_isValid": "0",
      "reARMP_rowIndex": 20
    }
  },
  "21": {
    "hostess_21": {
      "icon": 0,
      "reARMP_isValid": "0",
      "reARMP_rowIndex": 21
    }
  },
  "22": {
    "hostess_22": {
      "icon": 0,
      "reARMP_isValid": "0",
      "reARMP_rowIndex": 22
    }
  },
  "23": {
    "hostess_23": {
      "icon": 0,
      "reARMP_isValid": "0",
      "reARMP_rowIndex": 23
    }
  },
  "24": {
    "hostess_24": {
      "icon": 0,
      "reARMP_isValid": "0",
      "reARMP_rowIndex": 24
    }
  },
  "25": {
    "hostess_25": {
      "icon": 0,
      "reARMP_isValid": "0",
      "reARMP_rowIndex": 25
    }
  },
  "26": {
    "hostess_26": {
      "icon": 0,
      "reARMP_isValid": "0",
      "reARMP_rowIndex": 26
    }
  },
  "27": {
    "hostess_27": {
      "icon": 0,
      "reARMP_isValid": "0",
      "reARMP_rowIndex": 27
    }
  },
  "28": {
    "hostess_28": {
      "icon": 0,
      "reARMP_isValid": "0",
      "reARMP_rowIndex": 28
    }
  },
  "29": {
    "hostess_29": {
      "icon": 0,
      "reARMP_isValid": "0",
      "reARMP_rowIndex": 29
    }
  },
  "30": {
    "hostess_30": {
      "icon": 0,
      "reARMP_isValid": "0",
      "reARMP_rowIndex": 30
    }
  },
  "31": {
    "lip_01": {
      "name": "Activé",
      "explanation": "Changez la couleur des lèvres.",
      "icon": 3724,
      "reARMP_isValid": "1",
      "reARMP_rowIndex": 31
    }
  },
  "32": {
    "lip_02": {
      "icon": 0,
      "reARMP_isValid": "0",
      "reARMP_rowIndex": 32
    }
  },
  "33": {
    "lip_03": {
      "icon": 0,
      "reARMP_isValid": "0",
      "reARMP_rowIndex": 33
    }
  },
  "34": {
    "lip_04": {
      "icon": 0,
      "reARMP_isValid": "0",
      "reARMP_rowIndex": 34
    }
  },
  "35": {
    "lip_05": {
      "icon": 0,
      "reARMP_isValid": "0",
      "reARMP_rowIndex": 35
    }
  }
}